fastapi_payments/__init__.py
fastapi_payments/api/__init__.py
fastapi_payments/api/dependencies.py
fastapi_payments/api/routes.py
fastapi_payments/config/__init__.py
fastapi_payments/config/config_schema.py
fastapi_payments/config/settings.py
fastapi_payments/db/__init__.py
fastapi_payments/db/models.py
fastapi_payments/db/repositories/__init__.py
fastapi_payments/db/repositories/base.py
fastapi_payments/db/repositories/customer_repository.py
fastapi_payments/db/repositories/payment_method_repository.py
fastapi_payments/db/repositories/payment_repository.py
fastapi_payments/db/repositories/plan_repository.py
fastapi_payments/db/repositories/product_repository.py
fastapi_payments/db/repositories/subscription_repository.py
fastapi_payments/db/repositories/sync_job_repository.py
fastapi_payments/messaging/__init__.py
fastapi_payments/messaging/consumers.py
fastapi_payments/messaging/publishers.py
fastapi_payments/pricing/__init__.py
fastapi_payments/pricing/base.py
fastapi_payments/pricing/dynamic.py
fastapi_payments/pricing/freemium.py
fastapi_payments/pricing/hybrid.py
fastapi_payments/pricing/per_user.py
fastapi_payments/pricing/subscription.py
fastapi_payments/pricing/tiered.py
fastapi_payments/pricing/usage_based.py
fastapi_payments/providers/__init__.py
fastapi_payments/providers/adyen.py
fastapi_payments/providers/base.py
fastapi_payments/providers/paypal.py
fastapi_payments/providers/payu.py
fastapi_payments/providers/stripe.py
fastapi_payments/schemas/__init__.py
fastapi_payments/schemas/payment.py
fastapi_payments/schemas/pricing.py
fastapi_payments/services/__init__.py
fastapi_payments/services/payment_service.py
fastapi_payments/services/pricing_service.py
fastapi_payments/utils/__init__.py
fastapi_payments/utils/exceptions.py
fastapi_payments/utils/helpers.py
fastapi_payments-0.1.3.dist-info/METADATA
fastapi_payments-0.1.3.dist-info/WHEEL
fastapi_payments-0.1.3.dist-info/top_level.txt
fastapi_payments-0.1.3.dist-info/RECORD
