Metadata-Version: 2.4
Name: fastapi-payments
Version: 0.1.3
Summary: A flexible and extensible payment library for FastAPI
Author-email: InnerKore <gagan@innerkore.com>
License: MIT
Project-URL: Homepage, https://github.com/innerkorehq/fastapi-payments
Project-URL: Bug Tracker, https://github.com/innerkorehq/fastapi-payments/issues
Project-URL: Documentation, https://fastapi-payments.readthedocs.io/
Keywords: fastapi,payments,stripe,paypal,adyen,rabbitmq
Classifier: Programming Language :: Python :: 3
Classifier: Programming Language :: Python :: 3.8
Classifier: Programming Language :: Python :: 3.9
Classifier: Programming Language :: Python :: 3.10
Classifier: Programming Language :: Python :: 3.11
Classifier: Programming Language :: Python :: 3.12
Classifier: Programming Language :: Python :: 3.13
Classifier: License :: OSI Approved :: MIT License
Classifier: Operating System :: OS Independent
Classifier: Framework :: FastAPI
Classifier: Intended Audience :: Developers
Classifier: Topic :: Software Development :: Libraries :: Python Modules
Requires-Python: >=3.8
Requires-Dist: fastapi>=0.103.0
Requires-Dist: sqlalchemy>=2.0.0
Requires-Dist: asyncpg>=0.27.0
Requires-Dist: pydantic>=2.0.0
Requires-Dist: faststream[redis]>=0.2.0
Requires-Dist: aiohttp>=3.8.0
Requires-Dist: email-validator>=2.0.0
Provides-Extra: stripe
Requires-Dist: stripe>=6.0.0; extra == "stripe"
Provides-Extra: paypal
Requires-Dist: paypalrestsdk>=1.13.1; extra == "paypal"
Provides-Extra: adyen
Requires-Dist: Adyen>=13.0.0; extra == "adyen"
Provides-Extra: rabbitmq
Requires-Dist: faststream[rabbit]>=0.2.0; extra == "rabbitmq"
Provides-Extra: kafka
Requires-Dist: faststream[kafka]>=0.2.0; extra == "kafka"
Provides-Extra: nats
Requires-Dist: faststream[nats]>=0.2.0; extra == "nats"
Provides-Extra: all
Requires-Dist: stripe>=6.0.0; extra == "all"
Requires-Dist: paypalrestsdk>=1.13.1; extra == "all"
Requires-Dist: Adyen>=13.0.0; extra == "all"
Requires-Dist: faststream[kafka,nats,rabbit,redis]>=0.2.0; extra == "all"
Provides-Extra: dev
Requires-Dist: pytest>=7.0.0; extra == "dev"
Requires-Dist: pytest-asyncio>=0.21.0; extra == "dev"
Requires-Dist: flake8>=6.0.0; extra == "dev"
Requires-Dist: black>=23.0.0; extra == "dev"
Requires-Dist: mypy>=1.0.0; extra == "dev"
Requires-Dist: faststream[memory,rabbit]>=0.2.0; extra == "dev"
